q2report/__init__.py
q2report/q2engine/__init__.py
q2report/q2engine/q2engine_core.py
q2report/q2engine/q2engine_pyqt.py
q2report/q2printer/__init__.py
q2report/q2printer/calc_height.py
q2report/q2printer/docx_parts.py
q2report/q2printer/q2printer.py
q2report/q2printer/q2printer_docx.py
q2report/q2printer/q2printer_html.py
q2report/q2printer/q2printer_pdf.py
q2report/q2printer/q2printer_xlsx.py
q2report/q2printer/rich_text_parser.py
q2report/q2printer/xlsx_parts.py
q2report/q2report.py
q2report/q2utils.py
q2report/version.py
q2report-0.1.55.dist-info/LICENSE
q2report-0.1.55.dist-info/METADATA
q2report-0.1.55.dist-info/WHEEL
q2report-0.1.55.dist-info/RECORD
